{
    "profile": [
        {
            "timestamp": "2023-12-11 14:38:52+00:00",
            "data": {
                "id": "0fafba96-ee81-4688-bd3a-6c71c4ed6fe0",
                "updated_at": "2023-12-09T22:10:00.370243+00:00",
                "username": "storeting",
                "valid_from": "2023-12-09T22:10:57.969+00:00",
                "organization_id": 2
            }
        }
    ],
    "scoreboard": [],
    "current_info": {
        "score": "?",
        "num_solves": "?",
        "username": "storeting",
        "organization_id": 2
    }
}