{
    "profile": [
        {
            "timestamp": "2023-12-13 13:45:57+00:00",
            "data": {
                "id": "1c066e49-af39-4765-9276-b5218213cefd",
                "updated_at": "2023-12-13T13:37:11.871901+00:00",
                "username": "johs1",
                "valid_from": "2023-12-13T13:40:21.673+00:00",
                "organization_id": 2
            }
        }
    ],
    "scoreboard": [
        {
            "timestamp": "2023-12-13 17:45:56+00:00",
            "data": {
                "user_id": "1c066e49-af39-4765-9276-b5218213cefd",
                "username": "johs1",
                "score": 10,
                "num_solves": 1,
                "latest_solve_time": "2023-12-13T17:30:21.317857+00:00"
            }
        }
    ],
    "current_info": {
        "score": 10,
        "num_solves": 1,
        "username": "johs1",
        "organization_id": 2
    }
}