{
    "profile": [
        {
            "timestamp": "2023-12-01 18:45:03+00:00",
            "data": {
                "id": "27e7b6fa-5db6-45be-b334-f6397679b7ba",
                "updated_at": "2023-12-01T18:36:19.018064+00:00",
                "username": "ivareri",
                "valid_from": "2023-12-01T18:37:16.177+00:00",
                "organization_id": null
            }
        }
    ],
    "scoreboard": [
        {
            "timestamp": "2023-12-01 19:30:03+00:00",
            "data": {
                "user_id": "27e7b6fa-5db6-45be-b334-f6397679b7ba",
                "username": "ivareri",
                "score": 10,
                "num_solves": 1,
                "latest_solve_time": "2023-12-01T19:21:10.500469+00:00"
            }
        }
    ],
    "current_info": {
        "score": 10,
        "num_solves": 1,
        "username": "ivareri",
        "organization_id": null
    }
}