{
    "profile": [
        {
            "timestamp": "2023-12-16 00:46:06+00:00",
            "data": {
                "id": "2803e633-6202-44ec-a573-f1278b95e53a",
                "updated_at": "2023-12-16T00:30:32.86416+00:00",
                "username": null,
                "valid_from": "2023-12-16T00:30:32.86416+00:00",
                "organization_id": null
            }
        }
    ],
    "scoreboard": [],
    "current_info": {
        "score": "?",
        "num_solves": "?",
        "username": null,
        "organization_id": null
    }
}