{
    "profile": [
        {
            "timestamp": "2024-01-09 17:31:57+00:00",
            "data": {
                "id": "2b42ae0d-6b4c-48f5-bf01-d0f165bd2137",
                "updated_at": "2024-01-09T17:19:16.671564+00:00",
                "username": "magasb1",
                "valid_from": "2024-01-09T17:20:17.053+00:00",
                "organization_id": 1
            }
        }
    ],
    "scoreboard": [
        {
            "timestamp": "2024-01-09 18:46:58+00:00",
            "data": {
                "user_id": "2b42ae0d-6b4c-48f5-bf01-d0f165bd2137",
                "username": "magasb1",
                "score": 10,
                "num_solves": 1,
                "latest_solve_time": "2024-01-09T18:39:36.586461+00:00"
            }
        }
    ],
    "current_info": {
        "score": 10,
        "num_solves": 1,
        "username": "magasb1",
        "organization_id": 1
    }
}