{
    "profile": [
        {
            "timestamp": "2023-12-04 18:30:07+00:00",
            "data": {
                "id": "36245ce4-00bc-42c4-bf86-b736922a4160",
                "updated_at": "2023-12-04T18:15:40.986057+00:00",
                "username": "siliconcarne",
                "valid_from": "2023-12-04T18:16:32.425+00:00",
                "organization_id": 3
            }
        }
    ],
    "scoreboard": [],
    "current_info": {
        "score": "?",
        "num_solves": "?",
        "username": "siliconcarne",
        "organization_id": 3
    }
}