{
    "profile": [
        {
            "timestamp": "2023-12-01 12:02:06+00:00",
            "data": {
                "id": "6bd65db8-9bb0-4e72-b745-7ba16f8232ef",
                "updated_at": "2023-12-01T07:32:37.456424+00:00",
                "username": "CyRanger1",
                "valid_from": "2023-12-01T07:35:48.016+00:00",
                "organization_id": null
            }
        }
    ],
    "scoreboard": [],
    "current_info": {
        "score": "?",
        "num_solves": "?",
        "username": "CyRanger1",
        "organization_id": null
    }
}