{
    "profile": [
        {
            "timestamp": "2023-12-12 09:30:52+00:00",
            "data": {
                "id": "893d3e6c-88da-4a39-8a6e-08f4feaa09be",
                "updated_at": "2023-12-12T09:22:46.603326+00:00",
                "username": null,
                "valid_from": "2023-12-12T09:22:46.603326+00:00",
                "organization_id": null
            }
        },
        {
            "timestamp": "2023-12-12 12:45:52+00:00",
            "data": {
                "id": "893d3e6c-88da-4a39-8a6e-08f4feaa09be",
                "updated_at": "2023-12-12T09:22:46.603326+00:00",
                "username": null,
                "valid_from": "2023-12-12T12:36:20.291+00:00",
                "organization_id": 1
            }
        }
    ],
    "scoreboard": [],
    "current_info": {
        "score": "?",
        "num_solves": "?",
        "username": null,
        "organization_id": 1
    }
}