{
    "profile": [
        {
            "timestamp": "2023-12-15 09:46:05+00:00",
            "data": {
                "id": "c31310ca-dcc6-40c7-9282-88ba92252684",
                "updated_at": "2023-12-15T09:37:26.444363+00:00",
                "username": "Bennyw",
                "valid_from": "2023-12-15T09:38:11.177+00:00",
                "organization_id": 2
            }
        }
    ],
    "scoreboard": [],
    "current_info": {
        "score": "?",
        "num_solves": "?",
        "username": "Bennyw",
        "organization_id": 2
    }
}