{
    "profile": [
        {
            "timestamp": "2023-12-07 13:45:08+00:00",
            "data": {
                "id": "d6f8b3e3-cddb-442e-80e9-64c1ec623933",
                "updated_at": "2023-12-07T13:40:48.924222+00:00",
                "username": "nt-representin",
                "valid_from": "2023-12-07T13:42:20.821+00:00",
                "organization_id": 2
            }
        }
    ],
    "scoreboard": [
        {
            "timestamp": "2023-12-07 14:00:08+00:00",
            "data": {
                "user_id": "d6f8b3e3-cddb-442e-80e9-64c1ec623933",
                "username": "nt-representin",
                "score": 10,
                "num_solves": 1,
                "latest_solve_time": "2023-12-07T13:55:47.853084+00:00"
            }
        }
    ],
    "current_info": {
        "score": 10,
        "num_solves": 1,
        "username": "nt-representin",
        "organization_id": 2
    }
}